Topsis/TOPSIS.py
Topsis/__init__.py
Topsis_Aditya_102003706-0.1.5.dist-info/LICENSE
Topsis_Aditya_102003706-0.1.5.dist-info/METADATA
Topsis_Aditya_102003706-0.1.5.dist-info/WHEEL
Topsis_Aditya_102003706-0.1.5.dist-info/entry_points.txt
Topsis_Aditya_102003706-0.1.5.dist-info/top_level.txt
Topsis_Aditya_102003706-0.1.5.dist-info/RECORD
