Metadata-Version: 2.1
Name: Topsis-Aditya-102003706
Version: 0.1.5
Summary: Topsis, packaged for ease.
Author: Aditya Aggarwal
Author-email: aditya.agg7@gmail.com
Project-URL: Source, https://github.com/adityaagg7/Topsis-Package
Project-URL: Tracker, https://github.com/adityaagg7/Topsis-Package/issues
Classifier: Programming Language :: Python :: 3
Classifier: License :: OSI Approved :: MIT License
Classifier: Operating System :: OS Independent
Requires-Python: >=3.5
License-File: LICENSE
Requires-Dist: numpy
Requires-Dist: pandas
Requires-Dist: scikit-learn
